attr_analyst-0.1.7.dist-info/METADATA
attr_analyst-0.1.7.dist-info/WHEEL
attr_analyst/__init__.py
attr_analyst/core/attr_calculator.py
attr_analyst/io/__init__.py
attr_analyst/io/_relation.py
attr_analyst-0.1.7.dist-info/RECORD
