Metadata-Version: 2.1
Name: attr_analyst
Version: 0.1.7
Summary: Attributing changes in target metrics to related metrics and calculating the contribution values of the related metrics.
Author-Email: alithink <geekmobiler@gmail.com>
License: MIT
Requires-Python: >=3.9
Requires-Dist: pandas>=2.2.2
Requires-Dist: openpyxl>=3.1.5
